sensitivetickets/__init__.py
sensitivetickets/sensitivetickets.py
TracSensitiveTickets-1.2.4.dist-info/COPYING
TracSensitiveTickets-1.2.4.dist-info/METADATA
TracSensitiveTickets-1.2.4.dist-info/WHEEL
TracSensitiveTickets-1.2.4.dist-info/entry_points.txt
TracSensitiveTickets-1.2.4.dist-info/top_level.txt
TracSensitiveTickets-1.2.4.dist-info/RECORD
