Metadata-Version: 2.1
Name: TracSensitiveTickets
Version: 1.2.4
Summary: A trac plugin that lets you mark tickets as 'sensitive' with a check box.  Those tickets can only be seen with permission.
Home-page: https://trac-hacks.org/wiki/SensitiveTicketsPlugin
Author: Jeff Hammel, Sebastian Benthall, Rowan Wookey, Daniel Kahn Gillmor
Author-email: dkg@fifthhorseman.net
Maintainer: Daniel Kahn Gillmor
Maintainer-email: dkg@fifthhorseman.net
License: GPL
Keywords: trac plugin security
Platform: UNKNOWN
Classifier: Framework :: Trac
Requires-Dist: Trac
